{
    "高频操作词": {
        "切": [
            "调整",
            "处理",
            "修改",
            "改变"
        ],
        "拖": [
            "往后挪",
            "延迟",
            "放慢",
            "拉长"
        ],
        "透": [
            "穿透感",
            "通透度",
            "清晰感",
            "空气感"
        ],
        "亮": [
            "提高亮度",
            "增强高频",
            "提升光泽",
            "增加明亮度"
        ],
        "轻": [
            "减弱力度",
            "降低存在感",
            "柔和处理",
            "轻量化"
        ]
    },
    "程度描述": {
        "有点": [
            "稍微",
            "略微",
            "一点点",
            "一丢丢"
        ],
        "太": [
            "过于",
            "特别",
            "超级",
            "过分"
        ],
        "完全": [
            "彻底",
            "根本",
            "完全就是",
            "简直是"
        ],
        "很": [
            "有点太",
            "过于",
            "实在是有些",
            "我认为有些"
        ]
    },
    "核心名词": {
        "气势": [
            "冲击力",
            "力度",
            "力量感",
            "动态"
        ],
        "人声": [
            "主唱",
            "歌声",
            "vocal",
            "嗓子"
        ],
        "伴奏": [
            "bgm",
            "乐器",
            "beat",
            "配乐"
        ],
        "压缩": [
            "动态",
            "音量平衡",
            "力度调整",
            "动态处理"
        ],
        "混响": [
            "空间",
            "回声",
            "环境",
            "厅堂效果"
        ],
        "低频": [
            "低音能量",
            "鼓点力度",
            "厚度"
        ]
    },
    "形容词": {
        "弱": [
            "软",
            "虚",
            "没劲",
            "疲软"
        ],
        "punchy": [
            "带劲",
            "炸",
            "有力",
            "冲"
        ],
        "脏": [
            "糊",
            "闷",
            "浑",
            "不清爽"
        ]
    },
    "专业黑话": {
        "layback感": [
            "拖拍感",
            "滞后感",
            "放松感",
            "慵懒感"
        ],
        "空间感": [
            "立体感",
            "环绕感",
            "远近感",
            "3D感"
        ],
        "齿音": [
            "呲呲声",
            "高频刺音",
            "s音",
            "气声杂音"
        ],
        "掐着喉咙": [
            "压迫感",
            "声音紧",
            "憋闷感",
            "不舒展"
        ],
        "大舌头": [
            "模糊发音",
            "咬字不清"
        ]
    },
    "否定修饰": {
        "不": [
            "缺乏",
            "差点",
            "不足",
            "不够"
        ],
        "没": [
            "消失",
            "消退",
            "减弱"
        ]
    },
    "新增词汇": {
        "一点": [
            "一点",
            "一丢",
            "一些",
            "少点"
        ],
        "声音": [
            "音效",
            "嗓音",
            "声儿"
        ],
        "感觉": [
            "觉得",
            "听起来",
            "听起来像",
            "感觉像"
        ],
        "然后": [
            "接着",
            "之后",
            "再然后",
            "随后"
        ],
        "稍微": [
            "略带",
            "一点点",
            "少许",
            "轻微"
        ],
        "整体": [
            "全局",
            "总体",
            "全盘来看",
            "整体感觉"
        ],
        "想要": [
            "想",
            "希望",
            "打算",
            "期待"
        ],
        "就是": [
            "就是",
            "就是要",
            "就是说",
            "就"
        ],
        "干净": [
            "清晰",
            "透亮",
            "无杂音",
            "纯正"
        ],
        "还是": [
            "还是",
            "或是",
            "或者是",
            "还是说"
        ],
        "现在": [
            "目前",
            "此刻",
            "当下",
            "现在这会儿"
        ],
        "一些": [
            "一点",
            "少许",
            "几许",
            "些许"
        ],
        "一下": [
            "一下子",
            "一会儿",
            "一刻",
            "一瞬"
        ],
        "好像": [
            "似乎",
            "仿佛",
            "有点像",
            "差不多"
        ],
        "之后": [
            "之后",
            "过后",
            "接着",
            "然后"
        ],
        "往后": [
            "往后",
            "往后点",
            "再后面点",
            "靠后"
        ],
        "听感": [
            "感觉",
            "听起来",
            "声音效果"
        ],
        "耳朵": [
            "听觉",
            "听力",
            "耳朵"
        ],
        "再": [
            "再",
            "重新",
            "又"
        ],
        "听": [
            "听",
            "感受",
            "耳闻"
        ],
        "小": [
            "小小",
            "微小",
            "小小 bit"
        ],
        "大": [
            "重",
            "厚",
            "强"
        ],
        "把": [
            "将",
            "给",
            "把"
        ],
        "着": [
            "有",
            "带",
            "含"
        ],
        "想": [
            "想要",
            "希望",
            "觉得"
        ],
        "我": [
            "我",
            "咱",
            "自己"
        ]
    }
}